monaco_editors/__init__.py
monaco_editors/base.py
monaco_editors/config.py
monaco_editors/constants.py
monaco_editors/hashicorp-terraform.vsix
monaco_editors/lifespan_tasks.py
monaco_editors/models.py
monaco_editors/terraform.py
reflex_monaco_editor-1.0.3.dist-info/licenses/LICENSE
reflex_monaco_editor-1.0.3.dist-info/METADATA
reflex_monaco_editor-1.0.3.dist-info/WHEEL
reflex_monaco_editor-1.0.3.dist-info/top_level.txt
reflex_monaco_editor-1.0.3.dist-info/RECORD
