Metadata-Version: 2.4
Name: reflex-monaco-editor
Version: 1.0.3
Summary: Reflex Monaco Editor component with LSP capability
Author: riebecj
License:                                  Apache License
Project-URL: Repository, https://github.com/riebecj/reflex-monaco-editor
Project-URL: Issues, https://github.com/riebecj/reflex-monaco-editor/issues
Project-URL: Documentation, https://github.com/riebecj/reflex-monaco-editor?tab=readme-ov-file#reflex-monaco-editor
Keywords: reflex,reflex-custom-components,monaco
Classifier: Operating System :: OS Independent
Classifier: Development Status :: 3 - Alpha
Classifier: Environment :: Web Environment
Classifier: Intended Audience :: Developers
Classifier: Programming Language :: Python :: 3 :: Only
Classifier: Topic :: Software Development
Classifier: Topic :: Utilities
Requires-Python: >=3.11
License-File: LICENSE
Requires-Dist: reflex>=0.8.16
Requires-Dist: reflex-vite-config-plugin==0.0.4
Provides-Extra: dev
Requires-Dist: pytest~=7.4; extra == "dev"
Requires-Dist: pytest-cov~=4.1; extra == "dev"
Requires-Dist: pytest-asyncio~=0.23.8; extra == "dev"
Requires-Dist: uvicorn~=0.38.0; extra == "dev"
Requires-Dist: selenium~=4.38.0; extra == "dev"
Requires-Dist: pytest-playwright~=0.7.1; extra == "dev"
Requires-Dist: psutil~=7.1.2; extra == "dev"
Dynamic: license-file
